<annotation>
	<folder>0302</folder>
	<filename>0302-00000073.jpg</filename>
	<path>/home/vanejessi/vehicle dataset definitivo/images/0302/0302-00000073.jpg</path>
	<source>
		<database>Unknown</database>
	</source>
	<size>
		<width>482</width>
		<height>266</height>
		<depth>3</depth>
	</size>
	<segmented>0</segmented>
	<object>
		<name>car</name>
		<pose>Unspecified</pose>
		<truncated>0</truncated>
		<difficult>0</difficult>
		<bndbox>
			<xmin>107</xmin>
			<ymin>170</ymin>
			<xmax>152</xmax>
			<ymax>201</ymax>
		</bndbox>
	</object>
	<object>
		<name>car</name>
		<pose>Unspecified</pose>
		<truncated>0</truncated>
		<difficult>0</difficult>
		<bndbox>
			<xmin>292</xmin>
			<ymin>117</ymin>
			<xmax>313</xmax>
			<ymax>132</ymax>
		</bndbox>
	</object>
	<object>
		<name>car</name>
		<pose>Unspecified</pose>
		<truncated>0</truncated>
		<difficult>0</difficult>
		<bndbox>
			<xmin>308</xmin>
			<ymin>111</ymin>
			<xmax>324</xmax>
			<ymax>124</ymax>
		</bndbox>
	</object>
</annotation>
