<annotation>
	<folder>0401</folder>
	<filename>0401-00000097.jpg</filename>
	<path>/home/vanejessi/vehicle dataset definitivo/images/0401/0401-00000097.jpg</path>
	<source>
		<database>Unknown</database>
	</source>
	<size>
		<width>376</width>
		<height>266</height>
		<depth>3</depth>
	</size>
	<segmented>0</segmented>
	<object>
		<name>small-truck</name>
		<pose>Unspecified</pose>
		<truncated>1</truncated>
		<difficult>0</difficult>
		<bndbox>
			<xmin>16</xmin>
			<ymin>217</ymin>
			<xmax>75</xmax>
			<ymax>266</ymax>
		</bndbox>
	</object>
	<object>
		<name>tank-truck</name>
		<pose>Unspecified</pose>
		<truncated>0</truncated>
		<difficult>0</difficult>
		<bndbox>
			<xmin>144</xmin>
			<ymin>161</ymin>
			<xmax>181</xmax>
			<ymax>200</ymax>
		</bndbox>
	</object>
	<object>
		<name>car</name>
		<pose>Unspecified</pose>
		<truncated>0</truncated>
		<difficult>0</difficult>
		<bndbox>
			<xmin>139</xmin>
			<ymin>160</ymin>
			<xmax>154</xmax>
			<ymax>175</ymax>
		</bndbox>
	</object>
	<object>
		<name>car</name>
		<pose>Unspecified</pose>
		<truncated>0</truncated>
		<difficult>0</difficult>
		<bndbox>
			<xmin>110</xmin>
			<ymin>176</ymin>
			<xmax>137</xmax>
			<ymax>195</ymax>
		</bndbox>
	</object>
	<object>
		<name>car</name>
		<pose>Unspecified</pose>
		<truncated>0</truncated>
		<difficult>0</difficult>
		<bndbox>
			<xmin>93</xmin>
			<ymin>166</ymin>
			<xmax>115</xmax>
			<ymax>181</ymax>
		</bndbox>
	</object>
	<object>
		<name>car</name>
		<pose>Unspecified</pose>
		<truncated>0</truncated>
		<difficult>0</difficult>
		<bndbox>
			<xmin>165</xmin>
			<ymin>140</ymin>
			<xmax>181</xmax>
			<ymax>152</ymax>
		</bndbox>
	</object>
</annotation>
