<annotation>
	<folder>0401</folder>
	<filename>0401-00000047.jpg</filename>
	<path>/home/vanejessi/vehicle dataset definitivo/images/0401/0401-00000047.jpg</path>
	<source>
		<database>Unknown</database>
	</source>
	<size>
		<width>376</width>
		<height>266</height>
		<depth>3</depth>
	</size>
	<segmented>0</segmented>
	<object>
		<name>truck</name>
		<pose>Unspecified</pose>
		<truncated>0</truncated>
		<difficult>0</difficult>
		<bndbox>
			<xmin>170</xmin>
			<ymin>124</ymin>
			<xmax>204</xmax>
			<ymax>169</ymax>
		</bndbox>
	</object>
	<object>
		<name>car</name>
		<pose>Unspecified</pose>
		<truncated>0</truncated>
		<difficult>0</difficult>
		<bndbox>
			<xmin>156</xmin>
			<ymin>174</ymin>
			<xmax>178</xmax>
			<ymax>192</ymax>
		</bndbox>
	</object>
	<object>
		<name>car</name>
		<pose>Unspecified</pose>
		<truncated>0</truncated>
		<difficult>0</difficult>
		<bndbox>
			<xmin>213</xmin>
			<ymin>153</ymin>
			<xmax>230</xmax>
			<ymax>166</ymax>
		</bndbox>
	</object>
	<object>
		<name>car</name>
		<pose>Unspecified</pose>
		<truncated>0</truncated>
		<difficult>0</difficult>
		<bndbox>
			<xmin>277</xmin>
			<ymin>186</ymin>
			<xmax>302</xmax>
			<ymax>211</ymax>
		</bndbox>
	</object>
</annotation>
